AHU/Connect.py
AHU/GenericAHU.py
AHU/__init__.py
AHU/AirPort/AirPort.py
AHU/AirPort/__init__.py
AHU/Coil/CoolingCoil.py
AHU/Coil/CoolingCoil_Expert.py
AHU/Coil/CoolingCoil_Sensible.py
AHU/Coil/CoolingCoil_Tc.py
AHU/Coil/HeatingCoil.py
AHU/Coil/HeatingCoilNUT.py
AHU/Coil/__init__.py
AHU/FreshAir/AirMix.py
AHU/FreshAir/FreshAir.py
AHU/FreshAir/__init__.py
AHU/HeatRecovery/Heat_plate_exchanger.py
AHU/HeatRecovery/Thermal_wheel_exchanger.py
AHU/HeatRecovery/__init__.py
AHU/Humidification/Humidifier.py
AHU/Humidification/__init__.py
AHU/air_humide/PsychrometricChart.py
AHU/air_humide/__init__.py
AHU/air_humide/air_humide.py
AHU/air_humide/air_humide_NB.py
CEE/CEE.py
CEE/__init__.py
Facture/ATR_Transport_Distribution.py
Facture/SONALGAZ_Elec.py
Facture/SONALGAZ_gaz.py
Facture/TURPE.py
Facture/__init__.py
Facture/coefficients_elec.json
Facture/coefficients_gaz_ATRD.json
Facture/coefficients_gaz_ATRT.json
Facture/coefficients_gaz_TICGN.json
Facture/coefficients_sonalgaz_elec.json
Facture/coefficients_sonalgaz_gaz.json
Facture/test.py
Facture/test_dz21_gaz.py
Facture/test_dz41.py
Facture/test_dz42.py
HeatTransfer/CompositeWall.py
HeatTransfer/ParallelepipedicBody.py
HeatTransfer/PipeInsulationAnalysis.py
HeatTransfer/PlateHeatTransfer.py
HeatTransfer/__init__.py
IPMVP/IPMVP.py
IPMVP/__init__.py
MeteoCiel/DJU_costic.py
MeteoCiel/MeteoCiel_Scraping.py
MeteoCiel/MeteoCiel_dayScraping.py
MeteoCiel/__init__.py
NodeEditor/__init__.py
NodeEditor/setup.py
NodeEditor/tox.ini
NodeEditor/nodeeditor/__init__.py
NodeEditor/nodeeditor/node_content_widget.py
NodeEditor/nodeeditor/node_edge.py
NodeEditor/nodeeditor/node_edge_dragging.py
NodeEditor/nodeeditor/node_edge_validators.py
NodeEditor/nodeeditor/node_editor_widget.py
NodeEditor/nodeeditor/node_editor_window.py
NodeEditor/nodeeditor/node_graphics_cutline.py
NodeEditor/nodeeditor/node_graphics_edge.py
NodeEditor/nodeeditor/node_graphics_edge_path.py
NodeEditor/nodeeditor/node_graphics_node.py
energysystemmodels-20251205001.dist-info/licenses/LICENSE
energysystemmodels-20251205001.dist-info/METADATA
energysystemmodels-20251205001.dist-info/WHEEL
energysystemmodels-20251205001.dist-info/top_level.txt
energysystemmodels-20251205001.dist-info/RECORD
