Metadata-Version: 2.4
Name: energysystemmodels
Version: 20251205001
Summary: Energy systems models are the mathematical models that are developed in order to represent as reliably as possible various energy-related problems.
Author: Zoheir HADID
Author-email: zoheir.hadid@gmail.com
Project-URL: Documentation, https://energysystemmodels-tutorial.readthedocs.io/en/latest/
Classifier: Programming Language :: Python :: 3
Classifier: Programming Language :: Python :: 3.6
Classifier: Programming Language :: Python :: 3.7
Classifier: Programming Language :: Python :: 3.8
Classifier: Programming Language :: Python :: 3.9
Classifier: Programming Language :: Python :: 3.10
Classifier: License :: OSI Approved :: MIT License
Classifier: Operating System :: OS Independent
Requires-Python: >=3.7
License-File: LICENSE
Requires-Dist: pandas
Requires-Dist: pyfluids
Requires-Dist: pylab-sdk~=1.3.2
Requires-Dist: matplotlib
Requires-Dist: tkintertable~=1.3.3
Requires-Dist: numpy
Requires-Dist: pyqtgraph
Requires-Dist: thermochem
Requires-Dist: sip
Requires-Dist: PyQt-builder
Requires-Dist: PyQt5
Requires-Dist: scikit-learn
Requires-Dist: beautifulsoup4
Requires-Dist: tqdm
Requires-Dist: statsmodels
Requires-Dist: python-docx
Requires-Dist: pvlib
Requires-Dist: gekko
Requires-Dist: networkx
Dynamic: author
Dynamic: author-email
Dynamic: classifier
Dynamic: description
Dynamic: description-content-type
Dynamic: license-file
Dynamic: project-url
Dynamic: requires-dist
Dynamic: requires-python
Dynamic: summary
